{
  "docId": "B004BY23I8.story",
  "sentences": [
    {
      "index": 0,
      "tokens": [
        {
          "index": 1,
          "word": "Love",
          "originalText": "Love",
          "characterOffsetBegin": 0,
          "characterOffsetEnd": 4,
          "before": "",
          "after": " "
        },
        {
          "index": 2,
          "word": "the",
          "originalText": "the",
          "characterOffsetBegin": 5,
          "characterOffsetEnd": 8,
          "before": " ",
          "after": " "
        },
        {
          "index": 3,
          "word": "coconut",
          "originalText": "coconut",
          "characterOffsetBegin": 9,
          "characterOffsetEnd": 16,
          "before": " ",
          "after": " "
        },
        {
          "index": 4,
          "word": "flavor",
          "originalText": "flavor",
          "characterOffsetBegin": 17,
          "characterOffsetEnd": 23,
          "before": " ",
          "after": " "
        },
        {
          "index": 5,
          "word": "of",
          "originalText": "of",
          "characterOffsetBegin": 24,
          "characterOffsetEnd": 26,
          "before": " ",
          "after": " "
        },
        {
          "index": 6,
          "word": "this",
          "originalText": "this",
          "characterOffsetBegin": 27,
          "characterOffsetEnd": 31,
          "before": " ",
          "after": " "
        },
        {
          "index": 7,
          "word": "tea",
          "originalText": "tea",
          "characterOffsetBegin": 32,
          "characterOffsetEnd": 35,
          "before": " ",
          "after": ""
        },
        {
          "index": 8,
          "word": ".",
          "originalText": ".",
          "characterOffsetBegin": 35,
          "characterOffsetEnd": 36,
          "before": "",
          "after": "  "
        }
      ]
    },
    {
      "index": 1,
      "tokens": [
        {
          "index": 1,
          "word": "Two",
          "originalText": "Two",
          "characterOffsetBegin": 38,
          "characterOffsetEnd": 41,
          "before": "  ",
          "after": " "
        },
        {
          "index": 2,
          "word": "things",
          "originalText": "things",
          "characterOffsetBegin": 42,
          "characterOffsetEnd": 48,
          "before": " ",
          "after": " "
        },
        {
          "index": 3,
          "word": "I",
          "originalText": "I",
          "characterOffsetBegin": 49,
          "characterOffsetEnd": 50,
          "before": " ",
          "after": " "
        },
        {
          "index": 4,
          "word": "wish",
          "originalText": "wish",
          "characterOffsetBegin": 51,
          "characterOffsetEnd": 55,
          "before": " ",
          "after": " "
        },
        {
          "index": 5,
          "word": "were",
          "originalText": "were",
          "characterOffsetBegin": 56,
          "characterOffsetEnd": 60,
          "before": " ",
          "after": " "
        },
        {
          "index": 6,
          "word": "different-the",
          "originalText": "different-the",
          "characterOffsetBegin": 61,
          "characterOffsetEnd": 74,
          "before": " ",
          "after": " "
        },
        {
          "index": 7,
          "word": "metal",
          "originalText": "metal",
          "characterOffsetBegin": 75,
          "characterOffsetEnd": 80,
          "before": " ",
          "after": " "
        },
        {
          "index": 8,
          "word": "rim",
          "originalText": "rim",
          "characterOffsetBegin": 81,
          "characterOffsetEnd": 84,
          "before": " ",
          "after": " "
        },
        {
          "index": 9,
          "word": "is",
          "originalText": "is",
          "characterOffsetBegin": 85,
          "characterOffsetEnd": 87,
          "before": " ",
          "after": " "
        },
        {
          "index": 10,
          "word": "slightly",
          "originalText": "slightly",
          "characterOffsetBegin": 88,
          "characterOffsetEnd": 96,
          "before": " ",
          "after": " "
        },
        {
          "index": 11,
          "word": "sharp",
          "originalText": "sharp",
          "characterOffsetBegin": 97,
          "characterOffsetEnd": 102,
          "before": " ",
          "after": " "
        },
        {
          "index": 12,
          "word": "and",
          "originalText": "and",
          "characterOffsetBegin": 103,
          "characterOffsetEnd": 106,
          "before": " ",
          "after": " "
        },
        {
          "index": 13,
          "word": "you",
          "originalText": "you",
          "characterOffsetBegin": 107,
          "characterOffsetEnd": 110,
          "before": " ",
          "after": " "
        },
        {
          "index": 14,
          "word": "need",
          "originalText": "need",
          "characterOffsetBegin": 111,
          "characterOffsetEnd": 115,
          "before": " ",
          "after": " "
        },
        {
          "index": 15,
          "word": "to",
          "originalText": "to",
          "characterOffsetBegin": 116,
          "characterOffsetEnd": 118,
          "before": " ",
          "after": " "
        },
        {
          "index": 16,
          "word": "be",
          "originalText": "be",
          "characterOffsetBegin": 119,
          "characterOffsetEnd": 121,
          "before": " ",
          "after": " "
        },
        {
          "index": 17,
          "word": "careful",
          "originalText": "careful",
          "characterOffsetBegin": 122,
          "characterOffsetEnd": 129,
          "before": " ",
          "after": ""
        },
        {
          "index": 18,
          "word": ",",
          "originalText": ",",
          "characterOffsetBegin": 129,
          "characterOffsetEnd": 130,
          "before": "",
          "after": " "
        },
        {
          "index": 19,
          "word": "would",
          "originalText": "would",
          "characterOffsetBegin": 131,
          "characterOffsetEnd": 136,
          "before": " ",
          "after": " "
        },
        {
          "index": 20,
          "word": "prefer",
          "originalText": "prefer",
          "characterOffsetBegin": 137,
          "characterOffsetEnd": 143,
          "before": " ",
          "after": " "
        },
        {
          "index": 21,
          "word": "that",
          "originalText": "that",
          "characterOffsetBegin": 144,
          "characterOffsetEnd": 148,
          "before": " ",
          "after": " "
        },
        {
          "index": 22,
          "word": "they",
          "originalText": "they",
          "characterOffsetBegin": 149,
          "characterOffsetEnd": 153,
          "before": " ",
          "after": " "
        },
        {
          "index": 23,
          "word": "make",
          "originalText": "make",
          "characterOffsetBegin": 154,
          "characterOffsetEnd": 158,
          "before": " ",
          "after": " "
        },
        {
          "index": 24,
          "word": "this",
          "originalText": "this",
          "characterOffsetBegin": 159,
          "characterOffsetEnd": 163,
          "before": " ",
          "after": " "
        },
        {
          "index": 25,
          "word": "in",
          "originalText": "in",
          "characterOffsetBegin": 164,
          "characterOffsetEnd": 166,
          "before": " ",
          "after": " "
        },
        {
          "index": 26,
          "word": "larger",
          "originalText": "larger",
          "characterOffsetBegin": 167,
          "characterOffsetEnd": 173,
          "before": " ",
          "after": " "
        },
        {
          "index": 27,
          "word": "size",
          "originalText": "size",
          "characterOffsetBegin": 174,
          "characterOffsetEnd": 178,
          "before": " ",
          "after": " "
        },
        {
          "index": 28,
          "word": "-LRB-",
          "originalText": "(",
          "characterOffsetBegin": 179,
          "characterOffsetEnd": 180,
          "before": " ",
          "after": ""
        },
        {
          "index": 29,
          "word": "at",
          "originalText": "at",
          "characterOffsetBegin": 180,
          "characterOffsetEnd": 182,
          "before": "",
          "after": " "
        },
        {
          "index": 30,
          "word": "least",
          "originalText": "least",
          "characterOffsetBegin": 183,
          "characterOffsetEnd": 188,
          "before": " ",
          "after": " "
        },
        {
          "index": 31,
          "word": "16",
          "originalText": "16",
          "characterOffsetBegin": 189,
          "characterOffsetEnd": 191,
          "before": " ",
          "after": " "
        },
        {
          "index": 32,
          "word": "oz",
          "originalText": "oz",
          "characterOffsetBegin": 192,
          "characterOffsetEnd": 194,
          "before": " ",
          "after": ""
        },
        {
          "index": 33,
          "word": "-RRB-",
          "originalText": ")",
          "characterOffsetBegin": 194,
          "characterOffsetEnd": 195,
          "before": "",
          "after": ""
        },
        {
          "index": 34,
          "word": ".",
          "originalText": ".",
          "characterOffsetBegin": 195,
          "characterOffsetEnd": 196,
          "before": "",
          "after": ""
        }
      ]
    },
    {
      "index": 2,
      "tokens": [
        {
          "index": 1,
          "word": "Pacific",
          "originalText": "Pacific",
          "characterOffsetBegin": 196,
          "characterOffsetEnd": 203,
          "before": "",
          "after": " "
        },
        {
          "index": 2,
          "word": "Chai",
          "originalText": "Chai",
          "characterOffsetBegin": 204,
          "characterOffsetEnd": 208,
          "before": " ",
          "after": " "
        },
        {
          "index": 3,
          "word": "coconut",
          "originalText": "coconut",
          "characterOffsetBegin": 209,
          "characterOffsetEnd": 216,
          "before": " ",
          "after": " "
        },
        {
          "index": 4,
          "word": "Chai",
          "originalText": "Chai",
          "characterOffsetBegin": 217,
          "characterOffsetEnd": 221,
          "before": " ",
          "after": " "
        },
        {
          "index": 5,
          "word": "Latte",
          "originalText": "Latte",
          "characterOffsetBegin": 222,
          "characterOffsetEnd": 227,
          "before": " ",
          "after": " "
        },
        {
          "index": 6,
          "word": "is",
          "originalText": "is",
          "characterOffsetBegin": 228,
          "characterOffsetEnd": 230,
          "before": " ",
          "after": " "
        },
        {
          "index": 7,
          "word": "so",
          "originalText": "so",
          "characterOffsetBegin": 231,
          "characterOffsetEnd": 233,
          "before": " ",
          "after": " "
        },
        {
          "index": 8,
          "word": "good",
          "originalText": "good",
          "characterOffsetBegin": 234,
          "characterOffsetEnd": 238,
          "before": " ",
          "after": ""
        },
        {
          "index": 9,
          "word": ".",
          "originalText": ".",
          "characterOffsetBegin": 238,
          "characterOffsetEnd": 239,
          "before": "",
          "after": " "
        }
      ]
    },
    {
      "index": 3,
      "tokens": [
        {
          "index": 1,
          "word": "I",
          "originalText": "I",
          "characterOffsetBegin": 240,
          "characterOffsetEnd": 241,
          "before": " ",
          "after": " "
        },
        {
          "index": 2,
          "word": "have",
          "originalText": "have",
          "characterOffsetBegin": 242,
          "characterOffsetEnd": 246,
          "before": " ",
          "after": " "
        },
        {
          "index": 3,
          "word": "a",
          "originalText": "a",
          "characterOffsetBegin": 247,
          "characterOffsetEnd": 248,
          "before": " ",
          "after": " "
        },
        {
          "index": 4,
          "word": "cup",
          "originalText": "cup",
          "characterOffsetBegin": 249,
          "characterOffsetEnd": 252,
          "before": " ",
          "after": " "
        },
        {
          "index": 5,
          "word": "every",
          "originalText": "every",
          "characterOffsetBegin": 253,
          "characterOffsetEnd": 258,
          "before": " ",
          "after": " "
        },
        {
          "index": 6,
          "word": "morning",
          "originalText": "morning",
          "characterOffsetBegin": 259,
          "characterOffsetEnd": 266,
          "before": " ",
          "after": " "
        },
        {
          "index": 7,
          "word": "with",
          "originalText": "with",
          "characterOffsetBegin": 267,
          "characterOffsetEnd": 271,
          "before": " ",
          "after": " "
        },
        {
          "index": 8,
          "word": "my",
          "originalText": "my",
          "characterOffsetBegin": 272,
          "characterOffsetEnd": 274,
          "before": " ",
          "after": " "
        },
        {
          "index": 9,
          "word": "coconut",
          "originalText": "coconut",
          "characterOffsetBegin": 275,
          "characterOffsetEnd": 282,
          "before": " ",
          "after": " "
        },
        {
          "index": 10,
          "word": "oil",
          "originalText": "oil",
          "characterOffsetBegin": 283,
          "characterOffsetEnd": 286,
          "before": " ",
          "after": " "
        },
        {
          "index": 11,
          "word": "in",
          "originalText": "in",
          "characterOffsetBegin": 287,
          "characterOffsetEnd": 289,
          "before": " ",
          "after": " "
        },
        {
          "index": 12,
          "word": "it",
          "originalText": "it",
          "characterOffsetBegin": 290,
          "characterOffsetEnd": 292,
          "before": " ",
          "after": ""
        },
        {
          "index": 13,
          "word": ".",
          "originalText": ".",
          "characterOffsetBegin": 292,
          "characterOffsetEnd": 293,
          "before": "",
          "after": " "
        }
      ]
    },
    {
      "index": 4,
      "tokens": [
        {
          "index": 1,
          "word": "Also",
          "originalText": "Also",
          "characterOffsetBegin": 294,
          "characterOffsetEnd": 298,
          "before": " ",
          "after": " "
        },
        {
          "index": 2,
          "word": "getting",
          "originalText": "getting",
          "characterOffsetBegin": 299,
          "characterOffsetEnd": 306,
          "before": " ",
          "after": " "
        },
        {
          "index": 3,
          "word": "it",
          "originalText": "it",
          "characterOffsetBegin": 307,
          "characterOffsetEnd": 309,
          "before": " ",
          "after": " "
        },
        {
          "index": 4,
          "word": "through",
          "originalText": "through",
          "characterOffsetBegin": 310,
          "characterOffsetEnd": 317,
          "before": " ",
          "after": " "
        },
        {
          "index": 5,
          "word": "Amazon",
          "originalText": "Amazon",
          "characterOffsetBegin": 318,
          "characterOffsetEnd": 324,
          "before": " ",
          "after": " "
        },
        {
          "index": 6,
          "word": "is",
          "originalText": "is",
          "characterOffsetBegin": 325,
          "characterOffsetEnd": 327,
          "before": " ",
          "after": " "
        },
        {
          "index": 7,
          "word": "much",
          "originalText": "much",
          "characterOffsetBegin": 328,
          "characterOffsetEnd": 332,
          "before": " ",
          "after": " "
        },
        {
          "index": 8,
          "word": "cheaper",
          "originalText": "cheaper",
          "characterOffsetBegin": 333,
          "characterOffsetEnd": 340,
          "before": " ",
          "after": " "
        },
        {
          "index": 9,
          "word": "than",
          "originalText": "than",
          "characterOffsetBegin": 341,
          "characterOffsetEnd": 345,
          "before": " ",
          "after": " "
        },
        {
          "index": 10,
          "word": "at",
          "originalText": "at",
          "characterOffsetBegin": 346,
          "characterOffsetEnd": 348,
          "before": " ",
          "after": " "
        },
        {
          "index": 11,
          "word": "the",
          "originalText": "the",
          "characterOffsetBegin": 349,
          "characterOffsetEnd": 352,
          "before": " ",
          "after": " "
        },
        {
          "index": 12,
          "word": "store",
          "originalText": "store",
          "characterOffsetBegin": 353,
          "characterOffsetEnd": 358,
          "before": " ",
          "after": ""
        },
        {
          "index": 13,
          "word": ".",
          "originalText": ".",
          "characterOffsetBegin": 358,
          "characterOffsetEnd": 359,
          "before": "",
          "after": " "
        }
      ]
    },
    {
      "index": 5,
      "tokens": [
        {
          "index": 1,
          "word": "I",
          "originalText": "I",
          "characterOffsetBegin": 360,
          "characterOffsetEnd": 361,
          "before": " ",
          "after": " "
        },
        {
          "index": 2,
          "word": "live",
          "originalText": "live",
          "characterOffsetBegin": 362,
          "characterOffsetEnd": 366,
          "before": " ",
          "after": " "
        },
        {
          "index": 3,
          "word": "about",
          "originalText": "about",
          "characterOffsetBegin": 367,
          "characterOffsetEnd": 372,
          "before": " ",
          "after": " "
        },
        {
          "index": 4,
          "word": "an",
          "originalText": "an",
          "characterOffsetBegin": 373,
          "characterOffsetEnd": 375,
          "before": " ",
          "after": " "
        },
        {
          "index": 5,
          "word": "hour",
          "originalText": "hour",
          "characterOffsetBegin": 376,
          "characterOffsetEnd": 380,
          "before": " ",
          "after": " "
        },
        {
          "index": 6,
          "word": "from",
          "originalText": "from",
          "characterOffsetBegin": 381,
          "characterOffsetEnd": 385,
          "before": " ",
          "after": " "
        },
        {
          "index": 7,
          "word": "any",
          "originalText": "any",
          "characterOffsetBegin": 386,
          "characterOffsetEnd": 389,
          "before": " ",
          "after": " "
        },
        {
          "index": 8,
          "word": "grocery",
          "originalText": "grocery",
          "characterOffsetBegin": 390,
          "characterOffsetEnd": 397,
          "before": " ",
          "after": " "
        },
        {
          "index": 9,
          "word": "store",
          "originalText": "store",
          "characterOffsetBegin": 398,
          "characterOffsetEnd": 403,
          "before": " ",
          "after": " "
        },
        {
          "index": 10,
          "word": "and",
          "originalText": "and",
          "characterOffsetBegin": 404,
          "characterOffsetEnd": 407,
          "before": " ",
          "after": " "
        },
        {
          "index": 11,
          "word": "so",
          "originalText": "so",
          "characterOffsetBegin": 408,
          "characterOffsetEnd": 410,
          "before": " ",
          "after": " "
        },
        {
          "index": 12,
          "word": "it",
          "originalText": "it",
          "characterOffsetBegin": 411,
          "characterOffsetEnd": 413,
          "before": " ",
          "after": " "
        },
        {
          "index": 13,
          "word": "is",
          "originalText": "is",
          "characterOffsetBegin": 414,
          "characterOffsetEnd": 416,
          "before": " ",
          "after": " "
        },
        {
          "index": 14,
          "word": "nice",
          "originalText": "nice",
          "characterOffsetBegin": 417,
          "characterOffsetEnd": 421,
          "before": " ",
          "after": " "
        },
        {
          "index": 15,
          "word": "to",
          "originalText": "to",
          "characterOffsetBegin": 422,
          "characterOffsetEnd": 424,
          "before": " ",
          "after": " "
        },
        {
          "index": 16,
          "word": "be",
          "originalText": "be",
          "characterOffsetBegin": 425,
          "characterOffsetEnd": 427,
          "before": " ",
          "after": " "
        },
        {
          "index": 17,
          "word": "able",
          "originalText": "able",
          "characterOffsetBegin": 428,
          "characterOffsetEnd": 432,
          "before": " ",
          "after": " "
        },
        {
          "index": 18,
          "word": "to",
          "originalText": "to",
          "characterOffsetBegin": 433,
          "characterOffsetEnd": 435,
          "before": " ",
          "after": " "
        },
        {
          "index": 19,
          "word": "have",
          "originalText": "have",
          "characterOffsetBegin": 436,
          "characterOffsetEnd": 440,
          "before": " ",
          "after": " "
        },
        {
          "index": 20,
          "word": "it",
          "originalText": "it",
          "characterOffsetBegin": 441,
          "characterOffsetEnd": 443,
          "before": " ",
          "after": " "
        },
        {
          "index": 21,
          "word": "shipped",
          "originalText": "shipped",
          "characterOffsetBegin": 444,
          "characterOffsetEnd": 451,
          "before": " ",
          "after": " "
        },
        {
          "index": 22,
          "word": "to",
          "originalText": "to",
          "characterOffsetBegin": 452,
          "characterOffsetEnd": 454,
          "before": " ",
          "after": " "
        },
        {
          "index": 23,
          "word": "my",
          "originalText": "my",
          "characterOffsetBegin": 455,
          "characterOffsetEnd": 457,
          "before": " ",
          "after": " "
        },
        {
          "index": 24,
          "word": "door.This",
          "originalText": "door.This",
          "characterOffsetBegin": 458,
          "characterOffsetEnd": 467,
          "before": " ",
          "after": " "
        },
        {
          "index": 25,
          "word": "version",
          "originalText": "version",
          "characterOffsetBegin": 468,
          "characterOffsetEnd": 475,
          "before": " ",
          "after": " "
        },
        {
          "index": 26,
          "word": "of",
          "originalText": "of",
          "characterOffsetBegin": 476,
          "characterOffsetEnd": 478,
          "before": " ",
          "after": " "
        },
        {
          "index": 27,
          "word": "Pacific",
          "originalText": "Pacific",
          "characterOffsetBegin": 479,
          "characterOffsetEnd": 486,
          "before": " ",
          "after": " "
        },
        {
          "index": 28,
          "word": "Chai",
          "originalText": "Chai",
          "characterOffsetBegin": 487,
          "characterOffsetEnd": 491,
          "before": " ",
          "after": " "
        },
        {
          "index": 29,
          "word": "is",
          "originalText": "is",
          "characterOffsetBegin": 492,
          "characterOffsetEnd": 494,
          "before": " ",
          "after": " "
        },
        {
          "index": 30,
          "word": "pretty",
          "originalText": "pretty",
          "characterOffsetBegin": 495,
          "characterOffsetEnd": 501,
          "before": " ",
          "after": " "
        },
        {
          "index": 31,
          "word": "mild",
          "originalText": "mild",
          "characterOffsetBegin": 502,
          "characterOffsetEnd": 506,
          "before": " ",
          "after": ""
        },
        {
          "index": 32,
          "word": ".",
          "originalText": ".",
          "characterOffsetBegin": 506,
          "characterOffsetEnd": 507,
          "before": "",
          "after": "  "
        }
      ]
    },
    {
      "index": 6,
      "tokens": [
        {
          "index": 1,
          "word": "I",
          "originalText": "I",
          "characterOffsetBegin": 509,
          "characterOffsetEnd": 510,
          "before": "  ",
          "after": " "
        },
        {
          "index": 2,
          "word": "LOVE",
          "originalText": "LOVE",
          "characterOffsetBegin": 511,
          "characterOffsetEnd": 515,
          "before": " ",
          "after": " "
        },
        {
          "index": 3,
          "word": "coconut",
          "originalText": "coconut",
          "characterOffsetBegin": 516,
          "characterOffsetEnd": 523,
          "before": " ",
          "after": " "
        },
        {
          "index": 4,
          "word": "and",
          "originalText": "and",
          "characterOffsetBegin": 524,
          "characterOffsetEnd": 527,
          "before": " ",
          "after": " "
        },
        {
          "index": 5,
          "word": "can",
          "originalText": "can",
          "characterOffsetBegin": 528,
          "characterOffsetEnd": 531,
          "before": " ",
          "after": " "
        },
        {
          "index": 6,
          "word": "bearly",
          "originalText": "bearly",
          "characterOffsetBegin": 532,
          "characterOffsetEnd": 538,
          "before": " ",
          "after": ""
        },
        {
          "index": 7,
          "word": ",",
          "originalText": ",",
          "characterOffsetBegin": 538,
          "characterOffsetEnd": 539,
          "before": "",
          "after": " "
        },
        {
          "index": 8,
          "word": "if",
          "originalText": "if",
          "characterOffsetBegin": 540,
          "characterOffsetEnd": 542,
          "before": " ",
          "after": " "
        },
        {
          "index": 9,
          "word": "at",
          "originalText": "at",
          "characterOffsetBegin": 543,
          "characterOffsetEnd": 545,
          "before": " ",
          "after": " "
        },
        {
          "index": 10,
          "word": "all",
          "originalText": "all",
          "characterOffsetBegin": 546,
          "characterOffsetEnd": 549,
          "before": " ",
          "after": ""
        },
        {
          "index": 11,
          "word": ",",
          "originalText": ",",
          "characterOffsetBegin": 549,
          "characterOffsetEnd": 550,
          "before": "",
          "after": " "
        },
        {
          "index": 12,
          "word": "taste",
          "originalText": "taste",
          "characterOffsetBegin": 551,
          "characterOffsetEnd": 556,
          "before": " ",
          "after": " "
        },
        {
          "index": 13,
          "word": "it",
          "originalText": "it",
          "characterOffsetBegin": 557,
          "characterOffsetEnd": 559,
          "before": " ",
          "after": " "
        },
        {
          "index": 14,
          "word": "in",
          "originalText": "in",
          "characterOffsetBegin": 560,
          "characterOffsetEnd": 562,
          "before": " ",
          "after": " "
        },
        {
          "index": 15,
          "word": "this",
          "originalText": "this",
          "characterOffsetBegin": 563,
          "characterOffsetEnd": 567,
          "before": " ",
          "after": " "
        },
        {
          "index": 16,
          "word": "product",
          "originalText": "product",
          "characterOffsetBegin": 568,
          "characterOffsetEnd": 575,
          "before": " ",
          "after": ""
        },
        {
          "index": 17,
          "word": ".",
          "originalText": ".",
          "characterOffsetBegin": 575,
          "characterOffsetEnd": 576,
          "before": "",
          "after": "  "
        }
      ]
    },
    {
      "index": 7,
      "tokens": [
        {
          "index": 1,
          "word": "I",
          "originalText": "I",
          "characterOffsetBegin": 578,
          "characterOffsetEnd": 579,
          "before": "  ",
          "after": " "
        },
        {
          "index": 2,
          "word": "was",
          "originalText": "was",
          "characterOffsetBegin": 580,
          "characterOffsetEnd": 583,
          "before": " ",
          "after": " "
        },
        {
          "index": 3,
          "word": "glad",
          "originalText": "glad",
          "characterOffsetBegin": 584,
          "characterOffsetEnd": 588,
          "before": " ",
          "after": " "
        },
        {
          "index": 4,
          "word": "my",
          "originalText": "my",
          "characterOffsetBegin": 589,
          "characterOffsetEnd": 591,
          "before": " ",
          "after": " "
        },
        {
          "index": 5,
          "word": "six",
          "originalText": "six",
          "characterOffsetBegin": 592,
          "characterOffsetEnd": 595,
          "before": " ",
          "after": " "
        },
        {
          "index": 6,
          "word": "pack",
          "originalText": "pack",
          "characterOffsetBegin": 596,
          "characterOffsetEnd": 600,
          "before": " ",
          "after": " "
        },
        {
          "index": 7,
          "word": "was",
          "originalText": "was",
          "characterOffsetBegin": 601,
          "characterOffsetEnd": 604,
          "before": " ",
          "after": " "
        },
        {
          "index": 8,
          "word": "gone",
          "originalText": "gone",
          "characterOffsetBegin": 605,
          "characterOffsetEnd": 609,
          "before": " ",
          "after": " "
        },
        {
          "index": 9,
          "word": "so",
          "originalText": "so",
          "characterOffsetBegin": 610,
          "characterOffsetEnd": 612,
          "before": " ",
          "after": " "
        },
        {
          "index": 10,
          "word": "I",
          "originalText": "I",
          "characterOffsetBegin": 613,
          "characterOffsetEnd": 614,
          "before": " ",
          "after": " "
        },
        {
          "index": 11,
          "word": "could",
          "originalText": "could",
          "characterOffsetBegin": 615,
          "characterOffsetEnd": 620,
          "before": " ",
          "after": " "
        },
        {
          "index": 12,
          "word": "buy",
          "originalText": "buy",
          "characterOffsetBegin": 621,
          "characterOffsetEnd": 624,
          "before": " ",
          "after": " "
        },
        {
          "index": 13,
          "word": "something",
          "originalText": "something",
          "characterOffsetBegin": 625,
          "characterOffsetEnd": 634,
          "before": " ",
          "after": " "
        },
        {
          "index": 14,
          "word": "a",
          "originalText": "a",
          "characterOffsetBegin": 635,
          "characterOffsetEnd": 636,
          "before": " ",
          "after": " "
        },
        {
          "index": 15,
          "word": "little",
          "originalText": "little",
          "characterOffsetBegin": 637,
          "characterOffsetEnd": 643,
          "before": " ",
          "after": " "
        },
        {
          "index": 16,
          "word": "stronger",
          "originalText": "stronger",
          "characterOffsetBegin": 644,
          "characterOffsetEnd": 652,
          "before": " ",
          "after": ""
        },
        {
          "index": 17,
          "word": ".",
          "originalText": ".",
          "characterOffsetBegin": 652,
          "characterOffsetEnd": 653,
          "before": "",
          "after": "  "
        }
      ]
    },
    {
      "index": 8,
      "tokens": [
        {
          "index": 1,
          "word": "If",
          "originalText": "If",
          "characterOffsetBegin": 655,
          "characterOffsetEnd": 657,
          "before": "  ",
          "after": " "
        },
        {
          "index": 2,
          "word": "you",
          "originalText": "you",
          "characterOffsetBegin": 658,
          "characterOffsetEnd": 661,
          "before": " ",
          "after": " "
        },
        {
          "index": 3,
          "word": "like",
          "originalText": "like",
          "characterOffsetBegin": 662,
          "characterOffsetEnd": 666,
          "before": " ",
          "after": " "
        },
        {
          "index": 4,
          "word": "the",
          "originalText": "the",
          "characterOffsetBegin": 667,
          "characterOffsetEnd": 670,
          "before": " ",
          "after": " "
        },
        {
          "index": 5,
          "word": "mild",
          "originalText": "mild",
          "characterOffsetBegin": 671,
          "characterOffsetEnd": 675,
          "before": " ",
          "after": " "
        },
        {
          "index": 6,
          "word": "taste",
          "originalText": "taste",
          "characterOffsetBegin": 676,
          "characterOffsetEnd": 681,
          "before": " ",
          "after": " "
        },
        {
          "index": 7,
          "word": "of",
          "originalText": "of",
          "characterOffsetBegin": 682,
          "characterOffsetEnd": 684,
          "before": " ",
          "after": " "
        },
        {
          "index": 8,
          "word": "chai",
          "originalText": "chai",
          "characterOffsetBegin": 685,
          "characterOffsetEnd": 689,
          "before": " ",
          "after": " "
        },
        {
          "index": 9,
          "word": "and",
          "originalText": "and",
          "characterOffsetBegin": 690,
          "characterOffsetEnd": 693,
          "before": " ",
          "after": " "
        },
        {
          "index": 10,
          "word": "hint",
          "originalText": "hint",
          "characterOffsetBegin": 694,
          "characterOffsetEnd": 698,
          "before": " ",
          "after": " "
        },
        {
          "index": 11,
          "word": "of",
          "originalText": "of",
          "characterOffsetBegin": 699,
          "characterOffsetEnd": 701,
          "before": " ",
          "after": " "
        },
        {
          "index": 12,
          "word": "coconut",
          "originalText": "coconut",
          "characterOffsetBegin": 702,
          "characterOffsetEnd": 709,
          "before": " ",
          "after": ""
        },
        {
          "index": 13,
          "word": ",",
          "originalText": ",",
          "characterOffsetBegin": 709,
          "characterOffsetEnd": 710,
          "before": "",
          "after": " "
        },
        {
          "index": 14,
          "word": "it",
          "originalText": "it",
          "characterOffsetBegin": 711,
          "characterOffsetEnd": 713,
          "before": " ",
          "after": " "
        },
        {
          "index": 15,
          "word": "would",
          "originalText": "would",
          "characterOffsetBegin": 714,
          "characterOffsetEnd": 719,
          "before": " ",
          "after": " "
        },
        {
          "index": 16,
          "word": "be",
          "originalText": "be",
          "characterOffsetBegin": 720,
          "characterOffsetEnd": 722,
          "before": " ",
          "after": " "
        },
        {
          "index": 17,
          "word": "perfect",
          "originalText": "perfect",
          "characterOffsetBegin": 723,
          "characterOffsetEnd": 730,
          "before": " ",
          "after": ""
        },
        {
          "index": 18,
          "word": ".",
          "originalText": ".",
          "characterOffsetBegin": 730,
          "characterOffsetEnd": 731,
          "before": "",
          "after": "  "
        }
      ]
    },
    {
      "index": 9,
      "tokens": [
        {
          "index": 1,
          "word": "<a href=\"http://www.amazon.com/gp/product/B004BY23I8\">",
          "originalText": "<a href=\"http://www.amazon.com/gp/product/B004BY23I8\">",
          "characterOffsetBegin": 733,
          "characterOffsetEnd": 787,
          "before": "  ",
          "after": ""
        },
        {
          "index": 2,
          "word": "Pacific",
          "originalText": "Pacific",
          "characterOffsetBegin": 787,
          "characterOffsetEnd": 794,
          "before": "",
          "after": " "
        },
        {
          "index": 3,
          "word": "Chai",
          "originalText": "Chai",
          "characterOffsetBegin": 795,
          "characterOffsetEnd": 799,
          "before": " ",
          "after": " "
        },
        {
          "index": 4,
          "word": "Tea",
          "originalText": "Tea",
          "characterOffsetBegin": 800,
          "characterOffsetEnd": 803,
          "before": " ",
          "after": ""
        },
        {
          "index": 5,
          "word": ",",
          "originalText": ",",
          "characterOffsetBegin": 803,
          "characterOffsetEnd": 804,
          "before": "",
          "after": " "
        },
        {
          "index": 6,
          "word": "Coconut",
          "originalText": "Coconut",
          "characterOffsetBegin": 805,
          "characterOffsetEnd": 812,
          "before": " ",
          "after": " "
        },
        {
          "index": 7,
          "word": "Chai",
          "originalText": "Chai",
          "characterOffsetBegin": 813,
          "characterOffsetEnd": 817,
          "before": " ",
          "after": " "
        },
        {
          "index": 8,
          "word": "Latte",
          "originalText": "Latte",
          "characterOffsetBegin": 818,
          "characterOffsetEnd": 823,
          "before": " ",
          "after": ""
        },
        {
          "index": 9,
          "word": ",",
          "originalText": ",",
          "characterOffsetBegin": 823,
          "characterOffsetEnd": 824,
          "before": "",
          "after": " "
        },
        {
          "index": 10,
          "word": "10-Ounce",
          "originalText": "10-Ounce",
          "characterOffsetBegin": 825,
          "characterOffsetEnd": 833,
          "before": " ",
          "after": " "
        },
        {
          "index": 11,
          "word": "Cans",
          "originalText": "Cans",
          "characterOffsetBegin": 834,
          "characterOffsetEnd": 838,
          "before": " ",
          "after": " "
        },
        {
          "index": 12,
          "word": "-LRB-",
          "originalText": "(",
          "characterOffsetBegin": 839,
          "characterOffsetEnd": 840,
          "before": " ",
          "after": ""
        },
        {
          "index": 13,
          "word": "Pack",
          "originalText": "Pack",
          "characterOffsetBegin": 840,
          "characterOffsetEnd": 844,
          "before": "",
          "after": " "
        },
        {
          "index": 14,
          "word": "of",
          "originalText": "of",
          "characterOffsetBegin": 845,
          "characterOffsetEnd": 847,
          "before": " ",
          "after": " "
        },
        {
          "index": 15,
          "word": "6",
          "originalText": "6",
          "characterOffsetBegin": 848,
          "characterOffsetEnd": 849,
          "before": " ",
          "after": ""
        },
        {
          "index": 16,
          "word": "-RRB-",
          "originalText": ")",
          "characterOffsetBegin": 849,
          "characterOffsetEnd": 850,
          "before": "",
          "after": ""
        },
        {
          "index": 17,
          "word": "</a>",
          "originalText": "</a>",
          "characterOffsetBegin": 850,
          "characterOffsetEnd": 854,
          "before": "",
          "after": "\n"
        }
      ]
    },
    {
      "index": 10,
      "tokens": [
        {
          "index": 1,
          "word": "@highlight",
          "originalText": "@highlight",
          "characterOffsetBegin": 856,
          "characterOffsetEnd": 866,
          "before": "\n",
          "after": "\n"
        }
      ]
    },
    {
      "index": 11,
      "tokens": [
        {
          "index": 1,
          "word": "love",
          "originalText": "love",
          "characterOffsetBegin": 868,
          "characterOffsetEnd": 872,
          "before": "\n",
          "after": " "
        },
        {
          "index": 2,
          "word": "the",
          "originalText": "the",
          "characterOffsetBegin": 873,
          "characterOffsetEnd": 876,
          "before": " ",
          "after": " "
        },
        {
          "index": 3,
          "word": "coconut",
          "originalText": "coconut",
          "characterOffsetBegin": 877,
          "characterOffsetEnd": 884,
          "before": " ",
          "after": " "
        },
        {
          "index": 4,
          "word": "flavor",
          "originalText": "flavor",
          "characterOffsetBegin": 885,
          "characterOffsetEnd": 891,
          "before": " ",
          "after": "\n"
        }
      ]
    },
    {
      "index": 12,
      "tokens": [
        {
          "index": 1,
          "word": "@highlight",
          "originalText": "@highlight",
          "characterOffsetBegin": 893,
          "characterOffsetEnd": 903,
          "before": "\n",
          "after": "\n"
        }
      ]
    },
    {
      "index": 13,
      "tokens": [
        {
          "index": 1,
          "word": "so",
          "originalText": "so",
          "characterOffsetBegin": 905,
          "characterOffsetEnd": 907,
          "before": "\n",
          "after": " "
        },
        {
          "index": 2,
          "word": "good",
          "originalText": "good",
          "characterOffsetBegin": 908,
          "characterOffsetEnd": 912,
          "before": " ",
          "after": ""
        }
      ]
    }
  ]
}
